busycat/__init__.py
busycat/mysql.py
busycat-0.1.2.dist-info/LICENSE
busycat-0.1.2.dist-info/METADATA
busycat-0.1.2.dist-info/WHEEL
busycat-0.1.2.dist-info/top_level.txt
busycat-0.1.2.dist-info/RECORD
