Metadata-Version: 2.1
Name: busycat
Version: 0.1.2
Summary: selfmade pkg
Home-page: 
Author: busycat
Author-email: 
Classifier: Programming Language :: Python :: 3
Classifier: License :: OSI Approved :: MIT License
Classifier: Operating System :: OS Independent
License-File: LICENSE
Requires-Dist: pymysql
